mesc/__init__.py
mesc/exceptions.py
mesc/interface.py
mesc/load.py
mesc/network_names.py
mesc/network_utils.py
mesc/overrides.py
mesc/py.typed
mesc/types.py
mesc/validation.py
mesc-0.2.1.dist-info/WHEEL
mesc-0.2.1.dist-info/METADATA
mesc-0.2.1.dist-info/RECORD
